api_key/__init__.py
api_key/key.py
hw1_guansli-0.1.1.dist-info/METADATA
hw1_guansli-0.1.1.dist-info/WHEEL
hw1_guansli-0.1.1.dist-info/top_level.txt
hw1_guansli-0.1.1.dist-info/RECORD
