Metadata-Version: 2.1
Name: hw1-guansli
Version: 0.1.1
Summary: HWK1, how to make a python library.
Home-page: https://github.com/gl2392/hw1-guansli
Author: GuansLi
Author-email: example@email.com
License: MIT
Platform: UNKNOWN
Classifier: Intended Audience :: Developers
Classifier: License :: OSI Approved :: MIT License
Classifier: Programming Language :: Python
Classifier: Programming Language :: Python :: 3
Classifier: Programming Language :: Python :: 3.8
Classifier: Programming Language :: Python :: 3.9
Classifier: Operating System :: OS Independent
Requires-Dist: numpy
Requires-Dist: polygon-api-client
Requires-Dist: sqlalchemy
Requires-Dist: matplotlib
Requires-Dist: pandas
